[{"layer": 0, "pretrained_layers": 6, "trial": 0, "epoch": 0, "data": {"micro_auroc": 0.8583147525787354, "mcc": 0.36626517749853627}}, {"layer": 0, "pretrained_layers": 6, "trial": 0, "epoch": 1, "data": {"micro_auroc": 0.893288254737854, "mcc": 0.4644303249737988}}, {"layer": 0, "pretrained_layers": 6, "trial": 0, "epoch": 2, "data": {"micro_auroc": 0.8751440048217773, "mcc": 0.44717746828861504}}, {"layer": 0, "pretrained_layers": 6, "trial": 0, "epoch": 3, "data": {"micro_auroc": 0.8867209553718567, "mcc": 0.48788381734137143}}, {"layer": 0, "pretrained_layers": 6, "trial": 0, "epoch": 4, "data": {"micro_auroc": 0.898475170135498, "mcc": 0.5253617025048173}}, {"layer": 1, "pretrained_layers": 6, "trial": 0, "epoch": 0, "data": {"micro_auroc": 0.8671762347221375, "mcc": 0.42940933664474235}}, {"layer": 1, "pretrained_layers": 6, "trial": 0, "epoch": 1, "data": {"micro_auroc": 0.8870592713356018, "mcc": 0.46065634131304095}}, {"layer": 1, "pretrained_layers": 6, "trial": 0, "epoch": 2, "data": {"micro_auroc": 0.8494513034820557, "mcc": 0.43728265698899105}}, {"layer": 1, "pretrained_layers": 6, "trial": 0, "epoch": 3, "data": {"micro_auroc": 0.8839536905288696, "mcc": 0.487766278152463}}, {"layer": 1, "pretrained_layers": 6, "trial": 0, "epoch": 4, "data": {"micro_auroc": 0.8949525952339172, "mcc": 0.525607256426821}}, {"layer": 2, "pretrained_layers": 6, "trial": 0, "epoch": 0, "data": {"micro_auroc": 0.8724921941757202, "mcc": 0.410585232606173}}, {"layer": 2, "pretrained_layers": 6, "trial": 0, "epoch": 1, "data": {"micro_auroc": 0.8993688225746155, "mcc": 0.4662068491248153}}, {"layer": 2, "pretrained_layers": 6, "trial": 0, "epoch": 2, "data": {"micro_auroc": 0.8783632516860962, "mcc": 0.4801927407692484}}, {"layer": 2, "pretrained_layers": 6, "trial": 0, "epoch": 3, "data": {"micro_auroc": 0.8844316601753235, "mcc": 0.46002739667904347}}, {"layer": 2, "pretrained_layers": 6, "trial": 0, "epoch": 4, "data": {"micro_auroc": 0.8918523192405701, "mcc": 0.5213072218799152}}, {"layer": 3, "pretrained_layers": 6, "trial": 0, "epoch": 0, "data": {"micro_auroc": 0.8914992809295654, "mcc": 0.43617935997414053}}, {"layer": 3, "pretrained_layers": 6, "trial": 0, "epoch": 1, "data": {"micro_auroc": 0.9085446000099182, "mcc": 0.5184252766241433}}, {"layer": 3, "pretrained_layers": 6, "trial": 0, "epoch": 2, "data": {"micro_auroc": 0.8872556090354919, "mcc": 0.4879106254805766}}, {"layer": 3, "pretrained_layers": 6, "trial": 0, "epoch": 3, "data": {"micro_auroc": 0.891107976436615, "mcc": 0.47315446861981686}}, {"layer": 3, "pretrained_layers": 6, "trial": 0, "epoch": 4, "data": {"micro_auroc": 0.8953359723091125, "mcc": 0.502578467208421}}, {"layer": 4, "pretrained_layers": 6, "trial": 0, "epoch": 0, "data": {"micro_auroc": 0.8891489505767822, "mcc": 0.4473928945477085}}, {"layer": 4, "pretrained_layers": 6, "trial": 0, "epoch": 1, "data": {"micro_auroc": 0.9000217318534851, "mcc": 0.5018116288672865}}, {"layer": 4, "pretrained_layers": 6, "trial": 0, "epoch": 2, "data": {"micro_auroc": 0.8842281103134155, "mcc": 0.513942943460846}}, {"layer": 4, "pretrained_layers": 6, "trial": 0, "epoch": 3, "data": {"micro_auroc": 0.893547534942627, "mcc": 0.505050953455782}}, {"layer": 4, "pretrained_layers": 6, "trial": 0, "epoch": 4, "data": {"micro_auroc": 0.8837110996246338, "mcc": 0.4783800806004276}}, {"layer": 5, "pretrained_layers": 6, "trial": 0, "epoch": 0, "data": {"micro_auroc": 0.8822581768035889, "mcc": 0.4450577507463179}}, {"layer": 5, "pretrained_layers": 6, "trial": 0, "epoch": 1, "data": {"micro_auroc": 0.895943820476532, "mcc": 0.5180474010852761}}, {"layer": 5, "pretrained_layers": 6, "trial": 0, "epoch": 2, "data": {"micro_auroc": 0.8805396556854248, "mcc": 0.49434303840428107}}, {"layer": 5, "pretrained_layers": 6, "trial": 0, "epoch": 3, "data": {"micro_auroc": 0.890550434589386, "mcc": 0.5300790182236294}}, {"layer": 5, "pretrained_layers": 6, "trial": 0, "epoch": 4, "data": {"micro_auroc": 0.8766317963600159, "mcc": 0.4914940719626848}}, {"layer": 0, "pretrained_layers": 8, "trial": 0, "epoch": 0, "data": {"micro_auroc": 0.859416127204895, "mcc": 0.33258319219669563}}, {"layer": 0, "pretrained_layers": 8, "trial": 0, "epoch": 1, "data": {"micro_auroc": 0.8869311809539795, "mcc": 0.44534180110953486}}, {"layer": 0, "pretrained_layers": 8, "trial": 0, "epoch": 2, "data": {"micro_auroc": 0.8565599322319031, "mcc": 0.41791260061875357}}, {"layer": 0, "pretrained_layers": 8, "trial": 0, "epoch": 3, "data": {"micro_auroc": 0.8435253500938416, "mcc": 0.3744086567725117}}, {"layer": 0, "pretrained_layers": 8, "trial": 0, "epoch": 4, "data": {"micro_auroc": 0.8935580849647522, "mcc": 0.4982138853499529}}, {"layer": 1, "pretrained_layers": 8, "trial": 0, "epoch": 0, "data": {"micro_auroc": 0.8655585050582886, "mcc": 0.3609215579302501}}, {"layer": 1, "pretrained_layers": 8, "trial": 0, "epoch": 1, "data": {"micro_auroc": 0.8180184364318848, "mcc": 0.32102655972491584}}, {"layer": 1, "pretrained_layers": 8, "trial": 0, "epoch": 2, "data": {"micro_auroc": 0.8936569690704346, "mcc": 0.4616995881577382}}, {"layer": 1, "pretrained_layers": 8, "trial": 0, "epoch": 3, "data": {"micro_auroc": 0.8921246528625488, "mcc": 0.482026517528345}}, {"layer": 1, "pretrained_layers": 8, "trial": 0, "epoch": 4, "data": {"micro_auroc": 0.8982437252998352, "mcc": 0.5198018811830807}}, {"layer": 2, "pretrained_layers": 8, "trial": 0, "epoch": 0, "data": {"micro_auroc": 0.8717976212501526, "mcc": 0.37296961642377413}}, {"layer": 2, "pretrained_layers": 8, "trial": 0, "epoch": 1, "data": {"micro_auroc": 0.8945724964141846, "mcc": 0.47452229841058857}}, {"layer": 2, "pretrained_layers": 8, "trial": 0, "epoch": 2, "data": {"micro_auroc": 0.8848459720611572, "mcc": 0.4866531563898378}}, {"layer": 2, "pretrained_layers": 8, "trial": 0, "epoch": 3, "data": {"micro_auroc": 0.8980259895324707, "mcc": 0.5129824525341652}}, {"layer": 2, "pretrained_layers": 8, "trial": 0, "epoch": 4, "data": {"micro_auroc": 0.8836179971694946, "mcc": 0.5226004570459173}}, {"layer": 3, "pretrained_layers": 8, "trial": 0, "epoch": 0, "data": {"micro_auroc": 0.8729725480079651, "mcc": 0.39132514613908703}}, {"layer": 3, "pretrained_layers": 8, "trial": 0, "epoch": 1, "data": {"micro_auroc": 0.8860414028167725, "mcc": 0.4799543292775026}}, {"layer": 3, "pretrained_layers": 8, "trial": 0, "epoch": 2, "data": {"micro_auroc": 0.8926416039466858, "mcc": 0.502308510986697}}, {"layer": 3, "pretrained_layers": 8, "trial": 0, "epoch": 3, "data": {"micro_auroc": 0.8784372210502625, "mcc": 0.4915454162037999}}, {"layer": 3, "pretrained_layers": 8, "trial": 0, "epoch": 4, "data": {"micro_auroc": 0.8886297345161438, "mcc": 0.5332515970632048}}, {"layer": 4, "pretrained_layers": 8, "trial": 0, "epoch": 0, "data": {"micro_auroc": 0.8657013773918152, "mcc": 0.4039059513514441}}, {"layer": 4, "pretrained_layers": 8, "trial": 0, "epoch": 1, "data": {"micro_auroc": 0.8807072043418884, "mcc": 0.4885402950418979}}, {"layer": 4, "pretrained_layers": 8, "trial": 0, "epoch": 2, "data": {"micro_auroc": 0.889492392539978, "mcc": 0.4830936563644186}}, {"layer": 4, "pretrained_layers": 8, "trial": 0, "epoch": 3, "data": {"micro_auroc": 0.8735363483428955, "mcc": 0.469970239643435}}, {"layer": 4, "pretrained_layers": 8, "trial": 0, "epoch": 4, "data": {"micro_auroc": 0.8856768012046814, "mcc": 0.49311822171965525}}, {"layer": 5, "pretrained_layers": 8, "trial": 0, "epoch": 0, "data": {"micro_auroc": 0.8594188690185547, "mcc": 0.4364140296799218}}, {"layer": 5, "pretrained_layers": 8, "trial": 0, "epoch": 1, "data": {"micro_auroc": 0.8783447742462158, "mcc": 0.45994454962597214}}, {"layer": 5, "pretrained_layers": 8, "trial": 0, "epoch": 2, "data": {"micro_auroc": 0.8878349661827087, "mcc": 0.5126089782508019}}, {"layer": 5, "pretrained_layers": 8, "trial": 0, "epoch": 3, "data": {"micro_auroc": 0.8786568641662598, "mcc": 0.5173024678121375}}, {"layer": 5, "pretrained_layers": 8, "trial": 0, "epoch": 4, "data": {"micro_auroc": 0.8948999643325806, "mcc": 0.5155933853627809}}, {"layer": 6, "pretrained_layers": 8, "trial": 0, "epoch": 0, "data": {"micro_auroc": 0.8647558689117432, "mcc": 0.3929903988573093}}, {"layer": 6, "pretrained_layers": 8, "trial": 0, "epoch": 1, "data": {"micro_auroc": 0.8733614087104797, "mcc": 0.44805589664378725}}, {"layer": 6, "pretrained_layers": 8, "trial": 0, "epoch": 2, "data": {"micro_auroc": 0.8862990140914917, "mcc": 0.46379977411076384}}, {"layer": 6, "pretrained_layers": 8, "trial": 0, "epoch": 3, "data": {"micro_auroc": 0.8752319812774658, "mcc": 0.4744846778314356}}, {"layer": 6, "pretrained_layers": 8, "trial": 0, "epoch": 4, "data": {"micro_auroc": 0.8819565773010254, "mcc": 0.4792154396826567}}, {"layer": 7, "pretrained_layers": 8, "trial": 0, "epoch": 0, "data": {"micro_auroc": 0.8623256683349609, "mcc": 0.3903345671192488}}, {"layer": 7, "pretrained_layers": 8, "trial": 0, "epoch": 1, "data": {"micro_auroc": 0.8798063397407532, "mcc": 0.47752669462415914}}, {"layer": 7, "pretrained_layers": 8, "trial": 0, "epoch": 2, "data": {"micro_auroc": 0.888933002948761, "mcc": 0.49927521573824957}}, {"layer": 7, "pretrained_layers": 8, "trial": 0, "epoch": 3, "data": {"micro_auroc": 0.8841103911399841, "mcc": 0.5020495408809257}}, {"layer": 7, "pretrained_layers": 8, "trial": 0, "epoch": 4, "data": {"micro_auroc": 0.8872607350349426, "mcc": 0.48666793023477606}}, {"layer": 0, "trial": 0, "epoch": 0, "data": {"micro_auroc": 0.863772451877594, "mcc": 0.3711880450028144}, "pretrained_layers": 9}, {"layer": 0, "trial": 0, "epoch": 1, "data": {"micro_auroc": 0.8815566897392273, "mcc": 0.4387221523520749}, "pretrained_layers": 9}, {"layer": 0, "trial": 0, "epoch": 2, "data": {"micro_auroc": 0.8811683654785156, "mcc": 0.4329543032462354}, "pretrained_layers": 9}, {"layer": 0, "trial": 0, "epoch": 3, "data": {"micro_auroc": 0.8613283634185791, "mcc": 0.4177810909571848}, "pretrained_layers": 9}, {"layer": 0, "trial": 0, "epoch": 4, "data": {"micro_auroc": 0.8840883374214172, "mcc": 0.4696468001671769}, "pretrained_layers": 9}, {"layer": 0, "trial": 1, "epoch": 0, "data": {"micro_auroc": 0.867214560508728, "mcc": 0.365960460319327}, "pretrained_layers": 9}, {"layer": 0, "trial": 1, "epoch": 1, "data": {"micro_auroc": 0.8941435813903809, "mcc": 0.47933256477897673}, "pretrained_layers": 9}, {"layer": 0, "trial": 1, "epoch": 2, "data": {"micro_auroc": 0.877756655216217, "mcc": 0.44363169669937313}, "pretrained_layers": 9}, {"layer": 0, "trial": 1, "epoch": 3, "data": {"micro_auroc": 0.874742329120636, "mcc": 0.462267681323406}, "pretrained_layers": 9}, {"layer": 0, "trial": 1, "epoch": 4, "data": {"micro_auroc": 0.8711826801300049, "mcc": 0.47409545305080203}, "pretrained_layers": 9}, {"layer": 0, "trial": 2, "epoch": 0, "data": {"micro_auroc": 0.7290168404579163, "mcc": 0.28538570025665566}, "pretrained_layers": 9}, {"layer": 0, "trial": 2, "epoch": 1, "data": {"micro_auroc": 0.7877570986747742, "mcc": 0.4113590972418182}, "pretrained_layers": 9}, {"layer": 0, "trial": 2, "epoch": 2, "data": {"micro_auroc": 0.8441946506500244, "mcc": 0.43195097137550237}, "pretrained_layers": 9}, {"layer": 0, "trial": 2, "epoch": 3, "data": {"micro_auroc": 0.8411126732826233, "mcc": 0.4229621274291886}, "pretrained_layers": 9}, {"layer": 0, "trial": 2, "epoch": 4, "data": {"micro_auroc": 0.8916357159614563, "mcc": 0.4851337477456288}, "pretrained_layers": 9}, {"layer": 1, "trial": 0, "epoch": 0, "data": {"micro_auroc": 0.8855913877487183, "mcc": 0.4329357968742867}, "pretrained_layers": 9}, {"layer": 1, "trial": 0, "epoch": 1, "data": {"micro_auroc": 0.8836640119552612, "mcc": 0.467922328297527}, "pretrained_layers": 9}, {"layer": 1, "trial": 0, "epoch": 2, "data": {"micro_auroc": 0.8919548392295837, "mcc": 0.464065937980289}, "pretrained_layers": 9}, {"layer": 1, "trial": 0, "epoch": 3, "data": {"micro_auroc": 0.8740294575691223, "mcc": 0.4594790578401442}, "pretrained_layers": 9}, {"layer": 1, "trial": 0, "epoch": 4, "data": {"micro_auroc": 0.9033694863319397, "mcc": 0.5164652389867656}, "pretrained_layers": 9}, {"layer": 1, "trial": 1, "epoch": 0, "data": {"micro_auroc": 0.8627499938011169, "mcc": 0.3723465520980189}, "pretrained_layers": 9}, {"layer": 1, "trial": 1, "epoch": 1, "data": {"micro_auroc": 0.8866441249847412, "mcc": 0.4534499078280692}, "pretrained_layers": 9}, {"layer": 1, "trial": 1, "epoch": 2, "data": {"micro_auroc": 0.8839738368988037, "mcc": 0.4598594997095244}, "pretrained_layers": 9}, {"layer": 1, "trial": 1, "epoch": 3, "data": {"micro_auroc": 0.8848719596862793, "mcc": 0.453234566548836}, "pretrained_layers": 9}, {"layer": 1, "trial": 1, "epoch": 4, "data": {"micro_auroc": 0.8941637277603149, "mcc": 0.525813321305577}, "pretrained_layers": 9}, {"layer": 1, "trial": 2, "epoch": 0, "data": {"micro_auroc": 0.8683720827102661, "mcc": 0.40489287637943155}, "pretrained_layers": 9}, {"layer": 1, "trial": 2, "epoch": 1, "data": {"micro_auroc": 0.8808674216270447, "mcc": 0.44353827369894966}, "pretrained_layers": 9}, {"layer": 1, "trial": 2, "epoch": 2, "data": {"micro_auroc": 0.8763194680213928, "mcc": 0.4479006747727468}, "pretrained_layers": 9}, {"layer": 1, "trial": 2, "epoch": 3, "data": {"micro_auroc": 0.8889296650886536, "mcc": 0.4633291549644163}, "pretrained_layers": 9}, {"layer": 1, "trial": 2, "epoch": 4, "data": {"micro_auroc": 0.893464982509613, "mcc": 0.5188881925888791}, "pretrained_layers": 9}, {"layer": 2, "trial": 0, "epoch": 0, "data": {"micro_auroc": 0.8803635835647583, "mcc": 0.4154549609514707}, "pretrained_layers": 9}, {"layer": 2, "trial": 0, "epoch": 1, "data": {"micro_auroc": 0.8773188591003418, "mcc": 0.474633557917702}, "pretrained_layers": 9}, {"layer": 2, "trial": 0, "epoch": 2, "data": {"micro_auroc": 0.8890080451965332, "mcc": 0.48483016893974035}, "pretrained_layers": 9}, {"layer": 2, "trial": 0, "epoch": 3, "data": {"micro_auroc": 0.8636621236801147, "mcc": 0.43846144663154185}, "pretrained_layers": 9}, {"layer": 2, "trial": 0, "epoch": 4, "data": {"micro_auroc": 0.8907574415206909, "mcc": 0.5071397504725516}, "pretrained_layers": 9}, {"layer": 2, "trial": 1, "epoch": 0, "data": {"micro_auroc": 0.876380443572998, "mcc": 0.3918362075785606}, "pretrained_layers": 9}, {"layer": 2, "trial": 1, "epoch": 1, "data": {"micro_auroc": 0.8863356709480286, "mcc": 0.48267825828696076}, "pretrained_layers": 9}, {"layer": 2, "trial": 1, "epoch": 2, "data": {"micro_auroc": 0.8758692741394043, "mcc": 0.4608935482433903}, "pretrained_layers": 9}, {"layer": 2, "trial": 1, "epoch": 3, "data": {"micro_auroc": 0.8744879364967346, "mcc": 0.44361345469978186}, "pretrained_layers": 9}, {"layer": 2, "trial": 1, "epoch": 4, "data": {"micro_auroc": 0.8982232809066772, "mcc": 0.5177205947197203}, "pretrained_layers": 9}, {"layer": 2, "trial": 2, "epoch": 0, "data": {"micro_auroc": 0.8803606629371643, "mcc": 0.40652797678346986}, "pretrained_layers": 9}, {"layer": 2, "trial": 2, "epoch": 1, "data": {"micro_auroc": 0.8822842836380005, "mcc": 0.4731303549203911}, "pretrained_layers": 9}, {"layer": 2, "trial": 2, "epoch": 2, "data": {"micro_auroc": 0.8900821805000305, "mcc": 0.46093127685516827}, "pretrained_layers": 9}, {"layer": 2, "trial": 2, "epoch": 3, "data": {"micro_auroc": 0.8799623250961304, "mcc": 0.5168203925080143}, "pretrained_layers": 9}, {"layer": 2, "trial": 2, "epoch": 4, "data": {"micro_auroc": 0.8923734426498413, "mcc": 0.5338566794061378}, "pretrained_layers": 9}, {"layer": 3, "trial": 0, "epoch": 0, "data": {"micro_auroc": 0.880311906337738, "mcc": 0.4037278431915711}, "pretrained_layers": 9}, {"layer": 3, "trial": 0, "epoch": 1, "data": {"micro_auroc": 0.8868629336357117, "mcc": 0.4895816999846123}, "pretrained_layers": 9}, {"layer": 3, "trial": 0, "epoch": 2, "data": {"micro_auroc": 0.9047073125839233, "mcc": 0.5256495707526987}, "pretrained_layers": 9}, {"layer": 3, "trial": 0, "epoch": 3, "data": {"micro_auroc": 0.8829240202903748, "mcc": 0.4611476613667495}, "pretrained_layers": 9}, {"layer": 3, "trial": 0, "epoch": 4, "data": {"micro_auroc": 0.8938384652137756, "mcc": 0.5051258944178812}, "pretrained_layers": 9}, {"layer": 3, "trial": 1, "epoch": 0, "data": {"micro_auroc": 0.8791525959968567, "mcc": 0.42304634677820646}, "pretrained_layers": 9}, {"layer": 3, "trial": 1, "epoch": 1, "data": {"micro_auroc": 0.8866803646087646, "mcc": 0.4762896577492906}, "pretrained_layers": 9}, {"layer": 3, "trial": 1, "epoch": 2, "data": {"micro_auroc": 0.894726574420929, "mcc": 0.50731546766114}, "pretrained_layers": 9}, {"layer": 3, "trial": 1, "epoch": 3, "data": {"micro_auroc": 0.8949359655380249, "mcc": 0.5054524884321278}, "pretrained_layers": 9}, {"layer": 3, "trial": 1, "epoch": 4, "data": {"micro_auroc": 0.8853376507759094, "mcc": 0.5031159683277887}, "pretrained_layers": 9}, {"layer": 3, "trial": 2, "epoch": 0, "data": {"micro_auroc": 0.8773779273033142, "mcc": 0.3945422527718552}, "pretrained_layers": 9}, {"layer": 3, "trial": 2, "epoch": 1, "data": {"micro_auroc": 0.8768453598022461, "mcc": 0.47477110961174424}, "pretrained_layers": 9}, {"layer": 3, "trial": 2, "epoch": 2, "data": {"micro_auroc": 0.8959305882453918, "mcc": 0.5408634675273347}, "pretrained_layers": 9}, {"layer": 3, "trial": 2, "epoch": 3, "data": {"micro_auroc": 0.8970829844474792, "mcc": 0.49201848769352147}, "pretrained_layers": 9}, {"layer": 3, "trial": 2, "epoch": 4, "data": {"micro_auroc": 0.8946555852890015, "mcc": 0.5254907618606457}, "pretrained_layers": 9}, {"layer": 4, "trial": 0, "epoch": 0, "data": {"micro_auroc": 0.8760600686073303, "mcc": 0.39868304138004007}, "pretrained_layers": 9}, {"layer": 4, "trial": 0, "epoch": 1, "data": {"micro_auroc": 0.8900934457778931, "mcc": 0.48361283643191183}, "pretrained_layers": 9}, {"layer": 4, "trial": 0, "epoch": 2, "data": {"micro_auroc": 0.8885005116462708, "mcc": 0.49038662450424303}, "pretrained_layers": 9}, {"layer": 4, "trial": 0, "epoch": 3, "data": {"micro_auroc": 0.8994573354721069, "mcc": 0.5066219758032546}, "pretrained_layers": 9}, {"layer": 4, "trial": 0, "epoch": 4, "data": {"micro_auroc": 0.9007803201675415, "mcc": 0.5123163955721506}, "pretrained_layers": 9}, {"layer": 4, "trial": 1, "epoch": 0, "data": {"micro_auroc": 0.8787006139755249, "mcc": 0.4135017817763756}, "pretrained_layers": 9}, {"layer": 4, "trial": 1, "epoch": 1, "data": {"micro_auroc": 0.8772352337837219, "mcc": 0.47565340033163206}, "pretrained_layers": 9}, {"layer": 4, "trial": 1, "epoch": 2, "data": {"micro_auroc": 0.890443742275238, "mcc": 0.49965526851969216}, "pretrained_layers": 9}, {"layer": 4, "trial": 1, "epoch": 3, "data": {"micro_auroc": 0.8985500335693359, "mcc": 0.5142820851977136}, "pretrained_layers": 9}, {"layer": 4, "trial": 1, "epoch": 4, "data": {"micro_auroc": 0.8974413275718689, "mcc": 0.5227050046603942}, "pretrained_layers": 9}, {"layer": 4, "trial": 2, "epoch": 0, "data": {"micro_auroc": 0.8734442591667175, "mcc": 0.40305738075325376}, "pretrained_layers": 9}, {"layer": 4, "trial": 2, "epoch": 1, "data": {"micro_auroc": 0.8864222168922424, "mcc": 0.48787000851373713}, "pretrained_layers": 9}, {"layer": 4, "trial": 2, "epoch": 2, "data": {"micro_auroc": 0.8903409242630005, "mcc": 0.49503494619677074}, "pretrained_layers": 9}, {"layer": 4, "trial": 2, "epoch": 3, "data": {"micro_auroc": 0.8975300788879395, "mcc": 0.47777348154648835}, "pretrained_layers": 9}, {"layer": 4, "trial": 2, "epoch": 4, "data": {"micro_auroc": 0.8979342579841614, "mcc": 0.5086724629356991}, "pretrained_layers": 9}, {"layer": 5, "trial": 0, "epoch": 0, "data": {"micro_auroc": 0.8763879537582397, "mcc": 0.40489287637943155}, "pretrained_layers": 9}, {"layer": 5, "trial": 0, "epoch": 1, "data": {"micro_auroc": 0.9004931449890137, "mcc": 0.49422845942043037}, "pretrained_layers": 9}, {"layer": 5, "trial": 0, "epoch": 2, "data": {"micro_auroc": 0.9008437991142273, "mcc": 0.4744578256499048}, "pretrained_layers": 9}, {"layer": 5, "trial": 0, "epoch": 3, "data": {"micro_auroc": 0.8899797797203064, "mcc": 0.47052459768856825}, "pretrained_layers": 9}, {"layer": 5, "trial": 0, "epoch": 4, "data": {"micro_auroc": 0.8992193341255188, "mcc": 0.47902471767000027}, "pretrained_layers": 9}, {"layer": 5, "trial": 1, "epoch": 0, "data": {"micro_auroc": 0.8823308348655701, "mcc": 0.4077808355821793}, "pretrained_layers": 9}, {"layer": 5, "trial": 1, "epoch": 1, "data": {"micro_auroc": 0.898295521736145, "mcc": 0.478254386140767}, "pretrained_layers": 9}, {"layer": 5, "trial": 1, "epoch": 2, "data": {"micro_auroc": 0.8947621583938599, "mcc": 0.500580155647973}, "pretrained_layers": 9}, {"layer": 5, "trial": 1, "epoch": 3, "data": {"micro_auroc": 0.8931968212127686, "mcc": 0.46063322404717727}, "pretrained_layers": 9}, {"layer": 5, "trial": 1, "epoch": 4, "data": {"micro_auroc": 0.8952534198760986, "mcc": 0.5049182647427283}, "pretrained_layers": 9}, {"layer": 5, "trial": 2, "epoch": 0, "data": {"micro_auroc": 0.8785900473594666, "mcc": 0.4058738506790636}, "pretrained_layers": 9}, {"layer": 5, "trial": 2, "epoch": 1, "data": {"micro_auroc": 0.8992196321487427, "mcc": 0.4927131133018182}, "pretrained_layers": 9}, {"layer": 5, "trial": 2, "epoch": 2, "data": {"micro_auroc": 0.901457667350769, "mcc": 0.5160642145999266}, "pretrained_layers": 9}, {"layer": 5, "trial": 2, "epoch": 3, "data": {"micro_auroc": 0.8959459066390991, "mcc": 0.4770527415401873}, "pretrained_layers": 9}, {"layer": 5, "trial": 2, "epoch": 4, "data": {"micro_auroc": 0.8945465087890625, "mcc": 0.4893774233167267}, "pretrained_layers": 9}, {"layer": 6, "trial": 0, "epoch": 0, "data": {"micro_auroc": 0.8782945275306702, "mcc": 0.40398249944945785}, "pretrained_layers": 9}, {"layer": 6, "trial": 0, "epoch": 1, "data": {"micro_auroc": 0.8901075124740601, "mcc": 0.47595527997830595}, "pretrained_layers": 9}, {"layer": 6, "trial": 0, "epoch": 2, "data": {"micro_auroc": 0.8945968151092529, "mcc": 0.5023707863583408}, "pretrained_layers": 9}, {"layer": 6, "trial": 0, "epoch": 3, "data": {"micro_auroc": 0.8908936381340027, "mcc": 0.4751886970487545}, "pretrained_layers": 9}, {"layer": 6, "trial": 0, "epoch": 4, "data": {"micro_auroc": 0.8899224400520325, "mcc": 0.44559105009039807}, "pretrained_layers": 9}, {"layer": 6, "trial": 1, "epoch": 0, "data": {"micro_auroc": 0.8752475380897522, "mcc": 0.3924890287491904}, "pretrained_layers": 9}, {"layer": 6, "trial": 1, "epoch": 1, "data": {"micro_auroc": 0.8885310888290405, "mcc": 0.48330272308195094}, "pretrained_layers": 9}, {"layer": 6, "trial": 1, "epoch": 2, "data": {"micro_auroc": 0.8881970643997192, "mcc": 0.4771487583187348}, "pretrained_layers": 9}, {"layer": 6, "trial": 1, "epoch": 3, "data": {"micro_auroc": 0.8857288956642151, "mcc": 0.48688673972104124}, "pretrained_layers": 9}, {"layer": 6, "trial": 1, "epoch": 4, "data": {"micro_auroc": 0.895843505859375, "mcc": 0.4972505757874528}, "pretrained_layers": 9}, {"layer": 6, "trial": 2, "epoch": 0, "data": {"micro_auroc": 0.8823187947273254, "mcc": 0.43212490962534456}, "pretrained_layers": 9}, {"layer": 6, "trial": 2, "epoch": 1, "data": {"micro_auroc": 0.8930096626281738, "mcc": 0.49348645205596775}, "pretrained_layers": 9}, {"layer": 6, "trial": 2, "epoch": 2, "data": {"micro_auroc": 0.8887153267860413, "mcc": 0.4905512384587838}, "pretrained_layers": 9}, {"layer": 6, "trial": 2, "epoch": 3, "data": {"micro_auroc": 0.894393265247345, "mcc": 0.48336027776888724}, "pretrained_layers": 9}, {"layer": 6, "trial": 2, "epoch": 4, "data": {"micro_auroc": 0.8847911953926086, "mcc": 0.461112143615867}, "pretrained_layers": 9}, {"layer": 7, "trial": 0, "epoch": 0, "data": {"micro_auroc": 0.8678056001663208, "mcc": 0.3771073105638709}, "pretrained_layers": 9}, {"layer": 7, "trial": 0, "epoch": 1, "data": {"micro_auroc": 0.8923171758651733, "mcc": 0.4975449652209948}, "pretrained_layers": 9}, {"layer": 7, "trial": 0, "epoch": 2, "data": {"micro_auroc": 0.8855910897254944, "mcc": 0.48126917940870445}, "pretrained_layers": 9}, {"layer": 7, "trial": 0, "epoch": 3, "data": {"micro_auroc": 0.887665867805481, "mcc": 0.464725133627386}, "pretrained_layers": 9}, {"layer": 7, "trial": 0, "epoch": 4, "data": {"micro_auroc": 0.8848598599433899, "mcc": 0.45693684941613877}, "pretrained_layers": 9}, {"layer": 7, "trial": 1, "epoch": 0, "data": {"micro_auroc": 0.8715571165084839, "mcc": 0.3916345404444363}, "pretrained_layers": 9}, {"layer": 7, "trial": 1, "epoch": 1, "data": {"micro_auroc": 0.8924189209938049, "mcc": 0.49658956405659077}, "pretrained_layers": 9}, {"layer": 7, "trial": 1, "epoch": 2, "data": {"micro_auroc": 0.883784294128418, "mcc": 0.48097584150191436}, "pretrained_layers": 9}, {"layer": 7, "trial": 1, "epoch": 3, "data": {"micro_auroc": 0.8900066018104553, "mcc": 0.4804380932478975}, "pretrained_layers": 9}, {"layer": 7, "trial": 1, "epoch": 4, "data": {"micro_auroc": 0.8890769481658936, "mcc": 0.469928383665044}, "pretrained_layers": 9}, {"layer": 7, "trial": 2, "epoch": 0, "data": {"micro_auroc": 0.8736417889595032, "mcc": 0.39826026097569417}, "pretrained_layers": 9}, {"layer": 7, "trial": 2, "epoch": 1, "data": {"micro_auroc": 0.8933082818984985, "mcc": 0.49776647266969487}, "pretrained_layers": 9}, {"layer": 7, "trial": 2, "epoch": 2, "data": {"micro_auroc": 0.8859430551528931, "mcc": 0.47831021835118004}, "pretrained_layers": 9}, {"layer": 7, "trial": 2, "epoch": 3, "data": {"micro_auroc": 0.8878000974655151, "mcc": 0.47582263579898415}, "pretrained_layers": 9}, {"layer": 7, "trial": 2, "epoch": 4, "data": {"micro_auroc": 0.8787924647331238, "mcc": 0.4360775781211196}, "pretrained_layers": 9}, {"layer": 8, "trial": 0, "epoch": 0, "data": {"micro_auroc": 0.8690021634101868, "mcc": 0.3577666297317938}, "pretrained_layers": 9}, {"layer": 8, "trial": 0, "epoch": 1, "data": {"micro_auroc": 0.8952282667160034, "mcc": 0.4898155991095728}, "pretrained_layers": 9}, {"layer": 8, "trial": 0, "epoch": 2, "data": {"micro_auroc": 0.8936753273010254, "mcc": 0.49891040273909215}, "pretrained_layers": 9}, {"layer": 8, "trial": 0, "epoch": 3, "data": {"micro_auroc": 0.894591212272644, "mcc": 0.4717842286854376}, "pretrained_layers": 9}, {"layer": 8, "trial": 0, "epoch": 4, "data": {"micro_auroc": 0.8969951868057251, "mcc": 0.49989210867179057}, "pretrained_layers": 9}, {"layer": 8, "trial": 1, "epoch": 0, "data": {"micro_auroc": 0.8677877187728882, "mcc": 0.3622402328046928}, "pretrained_layers": 9}, {"layer": 8, "trial": 1, "epoch": 1, "data": {"micro_auroc": 0.896645188331604, "mcc": 0.5063716438694912}, "pretrained_layers": 9}, {"layer": 8, "trial": 1, "epoch": 2, "data": {"micro_auroc": 0.8920630812644958, "mcc": 0.4929033787210704}, "pretrained_layers": 9}, {"layer": 8, "trial": 1, "epoch": 3, "data": {"micro_auroc": 0.8944509029388428, "mcc": 0.4982151923921129}, "pretrained_layers": 9}, {"layer": 8, "trial": 1, "epoch": 4, "data": {"micro_auroc": 0.8931591510772705, "mcc": 0.48391095598725753}, "pretrained_layers": 9}, {"layer": 8, "trial": 2, "epoch": 0, "data": {"micro_auroc": 0.8722348809242249, "mcc": 0.3909363878929003}, "pretrained_layers": 9}, {"layer": 8, "trial": 2, "epoch": 1, "data": {"micro_auroc": 0.8961854577064514, "mcc": 0.5036636506902741}, "pretrained_layers": 9}, {"layer": 8, "trial": 2, "epoch": 2, "data": {"micro_auroc": 0.8944717645645142, "mcc": 0.5083264357780272}, "pretrained_layers": 9}, {"layer": 8, "trial": 2, "epoch": 3, "data": {"micro_auroc": 0.892151415348053, "mcc": 0.49998540537276087}, "pretrained_layers": 9}, {"layer": 8, "trial": 2, "epoch": 4, "data": {"micro_auroc": 0.8969794511795044, "mcc": 0.4929033787210704}, "pretrained_layers": 9}]